LICENSE
MANIFEST.in
README.rst
setup.py
blogodev/__init__.py
blogodev/blogodev.py
blogodev.egg-info/PKG-INFO
blogodev.egg-info/SOURCES.txt
blogodev.egg-info/dependency_links.txt
blogodev.egg-info/entry_points.txt
blogodev.egg-info/not-zip-safe
blogodev.egg-info/requires.txt
blogodev.egg-info/top_level.txt