Metadata-Version: 1.0
Name: blogodev
Version: 0.1.3
Summary: An interim front end for blogofile development
Home-page: https://bitbucket.org/zzzeek/blogodev
Author: Mike Bayer
Author-email: mike@zzzcomputing.com
License: MIT
Keywords: Blogofile
Platform: UNKNOWN
Classifier: Development Status :: 3 - Alpha
Classifier: Environment :: Console
Classifier: Intended Audience :: Developers
Classifier: Programming Language :: Python
Classifier: Programming Language :: Python :: 3
Classifier: Programming Language :: Python :: Implementation :: CPython
Classifier: Programming Language :: Python :: Implementation :: PyPy
